kamping/.DS_Store
kamping/__init__.py
kamping/dataset/__init__.py
kamping/dataset/data.py
kamping/dataset/dataloader.py
kamping/dataset/test.py
kamping/kegg_parser/__init__.py
kamping/kegg_parser/call.py
kamping/kegg_parser/convert.py
kamping/kegg_parser/network.py
kamping/kegg_parser/protein_metabolite_parser.py
kamping/kegg_parser/utils.py
kamping/main.py
kamping/mol/__init__.py
kamping/mol/mol_scrapper.py
kamping/mol/mol_transformer.py
kamping/mol/utils.py
kamping/scaper/__init__.py
kamping/scaper/mol_file.mol
kamping/uniprot/__init__.py
kamping/uniprot/embedding.py
kamping/uniprot/parser.py
kamping/uniprot/uniprot.py
kamping/uniprot/utils.py
kamping/utils.py
kamping-0.1.dist-info/LICENSE
kamping-0.1.dist-info/METADATA
kamping-0.1.dist-info/WHEEL
kamping-0.1.dist-info/entry_points.txt
kamping-0.1.dist-info/RECORD
