Metadata-Version: 2.1
Name: kamping
Version: 0.1
Summary: KEGG automated metabolite protein interaction network for graph-model (KAMPING)
License: LICENSE
Author: Chunhui Gu
Author-email: cgu3@mdanderson.org
Requires-Python: >=3.10,<4.0
Classifier: License :: Other/Proprietary License
Classifier: Programming Language :: Python :: 3
Classifier: Programming Language :: Python :: 3.10
Classifier: Programming Language :: Python :: 3.11
Classifier: Programming Language :: Python :: 3.12
Requires-Dist: click (>=8.1.3,<9.0.0)
Requires-Dist: h5py (>=3.12.1,<4.0.0)
Requires-Dist: networkx (>=3.1,<4.0)
Requires-Dist: numpy
Requires-Dist: pandas
Requires-Dist: pathlib (>=1.0.1,<2.0.0)
Requires-Dist: rdkit (>=2024.3.5,<2025.0.0)
Requires-Dist: requests (>=2.31.0,<3.0.0)
Requires-Dist: scikit-mol (>=0.3.1,<0.4.0)
Requires-Dist: torch (>=1.13,<2.0)
Requires-Dist: torch-geometric (>=2.6.1,<3.0.0)
Requires-Dist: type-extensions (>=0.1.2,<0.2.0)
Requires-Dist: typer (==0.12.1)
Requires-Dist: unipressed (>=1.4.0,<2.0.0)
